toololol/__init__.py
toololol/function.py
toololol/function_examples.py
toololol/log.py
toololol/run.py
toololol/types.py
toololol-0.1.0.dist-info/licenses/LICENSE
toololol-0.1.0.dist-info/METADATA
toololol-0.1.0.dist-info/WHEEL
toololol-0.1.0.dist-info/top_level.txt
toololol-0.1.0.dist-info/RECORD
