Metadata-Version: 2.4
Name: toololol
Version: 0.1.0
Summary: Minimal Python function calling for Claude
Home-page: https://github.com/andreasjansson/toololol
Author: Andreas Jansson
Classifier: Programming Language :: Python :: 3
Classifier: License :: OSI Approved :: MIT License
Classifier: Operating System :: OS Independent
Requires-Python: >=3.7
License-File: LICENSE
Requires-Dist: anthropic<1,>=0.51.0
Dynamic: author
Dynamic: classifier
Dynamic: description
Dynamic: description-content-type
Dynamic: home-page
Dynamic: license-file
Dynamic: requires-dist
Dynamic: requires-python
Dynamic: summary
